etc/dbus-1/system.d/org.pop_os.repolib.conf
repolib/__init__.py
repolib/__version__.py
repolib/deb.py
repolib/deb_test.py
repolib/legacy_deb.py
repolib/legacy_deb_test.py
repolib/ppa.py
repolib/ppa_test.py
repolib/source.py
repolib/source_test.py
repolib/system.py
repolib/system_test.py
repolib/util.py
repolib/command/__init__.py
repolib/command/add.py
repolib/command/argparser.py
repolib/command/command.py
repolib/command/list.py
repolib/command/modify.py
repolib/command/remove.py
repolib/command/source.py
repolib-1.5.1.data/data/share/bash-completion/completions/apt-manage
repolib-1.5.1.data/data/share/zsh/vendor-completions/_apt-manage
repolib-1.5.1.data/scripts/apt-manage
usr/lib/repolib/add-apt-repository
usr/lib/repolib/service.py
usr/share/dbus-1/system-services/org.pop_os.repolib.service
usr/share/polkit-1/actions/org.pop_os.repolib.policy
repolib-1.5.1.dist-info/LICENSE
repolib-1.5.1.dist-info/LICENSE.LESSER
repolib-1.5.1.dist-info/METADATA
repolib-1.5.1.dist-info/WHEEL
repolib-1.5.1.dist-info/top_level.txt
repolib-1.5.1.dist-info/RECORD
