Metadata-Version: 2.1
Name: repolib
Version: 1.5.1
Summary: Easily manage software sources
Home-page: https://github.com/pop-os/repolib
Author: Ian Santopietro
Author-email: ian@system76.com
License: LGPLv3
Download-URL: https://github.com/pop-os/repolib/releases
Platform: UNKNOWN
